sopel_npm/__init__.py
sopel_npm/api.py
sopel_npm/errors.py
sopel_npm/plugin.py
sopel_npm/util.py
sopel_npm-0.1.0.dist-info/COPYING
sopel_npm-0.1.0.dist-info/METADATA
sopel_npm-0.1.0.dist-info/WHEEL
sopel_npm-0.1.0.dist-info/entry_points.txt
sopel_npm-0.1.0.dist-info/top_level.txt
sopel_npm-0.1.0.dist-info/RECORD
